setup.py
tests/__init__.py
tests/testall.py
webskewer/__init__.py
webskewer.http.egg-info/PKG-INFO
webskewer.http.egg-info/SOURCES.txt
webskewer.http.egg-info/dependency_links.txt
webskewer.http.egg-info/namespace_packages.txt
webskewer.http.egg-info/requires.txt
webskewer.http.egg-info/top_level.txt
webskewer/http/__init__.py
webskewer/http/exceptions.py
webskewer/http/grammar.py
webskewer/http/headers.py
webskewer/http/log.py
webskewer/http/main.py
webskewer/http/message.py
webskewer/http/range_util.py
webskewer/http/recv.py
webskewer/http/serve.py
webskewer/http/static_files.py
webskewer/http/status.py
webskewer/http/time_util.py
webskewer/http/util.py
webskewer/http/wsgi.py
